storekit/__init__.py
storekit/admin.py
storekit/apps.py
storekit/appstore.py
storekit/errors.py
storekit/fields.py
storekit/migrations/0001_initial.py
storekit/migrations/0002_auto_20171218_2351.py
storekit/migrations/0003_auto_20171219_0021.py
storekit/migrations/0004_auto_20180605_1629.py
storekit/migrations/0005_auto_20180609_1654.py
storekit/migrations/__init__.py
storekit/models.py
storekit/receipt.py
django_ios_storekit-1.0.10.dist-info/LICENSE
django_ios_storekit-1.0.10.dist-info/WHEEL
django_ios_storekit-1.0.10.dist-info/METADATA
django_ios_storekit-1.0.10.dist-info/RECORD
