Metadata-Version: 2.1
Name: django-ios-storekit
Version: 1.0.10
Summary: iOS In-App Purchase's receipt validation server plugin for Django
Home-page: https://github.com/nnsnodnb/django-ios-storekit
License: MIT
Keywords: django,ios,in-app-purchases,apple
Author: Yuya Oka
Author-email: nnsnodnb@gmail.com
Requires-Python: >=3.6,<4.0
Classifier: Environment :: Web Environment
Classifier: Framework :: Django
Classifier: Intended Audience :: Developers
Classifier: License :: OSI Approved :: MIT License
Classifier: Programming Language :: Python
Classifier: Programming Language :: Python :: 3
Classifier: Programming Language :: Python :: 3.10
Classifier: Programming Language :: Python :: 3.6
Classifier: Programming Language :: Python :: 3.7
Classifier: Programming Language :: Python :: 3.8
Classifier: Programming Language :: Python :: 3.9
Classifier: Topic :: Internet :: WWW/HTTP
Classifier: Topic :: Software Development :: Libraries :: Application Frameworks
Classifier: Topic :: Software Development :: Libraries :: Python Modules
Requires-Dist: Django (>=2,<4)
Requires-Dist: requests (>=2,<3)
Project-URL: Repository, https://github.com/nnsnodnb/django-ios-storekit
